{
  "kind": "collectionType",
  "collectionName": "variants",
  "info": {
    "singularName": "variant",
    "pluralName": "variants",
    "displayName": "Variant",
    "description": ""
  },
  "options": {
    "draftAndPublish": true
  },
  "pluginOptions": {},
  "attributes": {
    "code": {
      "type": "string",
      "required": true
    },
    "name": {
      "type": "string"
    },
    "stock": {
      "type": "integer",
      "default": 0,
      "required": true,
      "min": 0
    },
    "priceDelta": {
      "type": "integer"
    },
    "product": {
      "type": "relation",
      "relation": "oneToOne",
      "target": "api::product.product"
    }
  }
}
